dash_antd_components/Radio.py
dash_antd_components/Select.py
dash_antd_components/__init__.py
dash_antd_components/_imports_.py
dash_antd_components/antd.min.css
dash_antd_components/dash_antd_components.min.js
dash_antd_components/dash_antd_components.min.js.map
dash_antd_components/metadata.json
dash_antd_components/package-info.json
dash_antd_components/react-select@1.0.0-rc.10.min.css
dash_antd_components/version.py
dash_antd_components-0.0.1rc2.dist-info/LICENSE
dash_antd_components-0.0.1rc2.dist-info/METADATA
dash_antd_components-0.0.1rc2.dist-info/WHEEL
dash_antd_components-0.0.1rc2.dist-info/top_level.txt
dash_antd_components-0.0.1rc2.dist-info/RECORD
